avpackv5/AVPack.py
avpackv5/__init__.py
avpackv5-1.1.0.dist-info/LICENSE
avpackv5-1.1.0.dist-info/METADATA
avpackv5-1.1.0.dist-info/WHEEL
avpackv5-1.1.0.dist-info/RECORD
