Metadata-Version: 2.1
Name: avpackv5
Version: 1.1.0
Summary: Idk
Home-page: https://gist.github.com/AVirus-ubuntu/196b431c8ee73c99d9268d4df0022267
License: MIT
Keywords: avirus,python
Author: AVirus-ubuntu
Author-email: ribavan123wawa@gmail.com
Requires-Python: >=3.7,<4.0
Classifier: License :: OSI Approved :: MIT License
Classifier: Programming Language :: Python :: 3
Classifier: Programming Language :: Python :: 3.7
Classifier: Programming Language :: Python :: 3.8
Classifier: Programming Language :: Python :: 3.9
Classifier: Programming Language :: Python :: 3.10
Classifier: Programming Language :: Python :: 3.11
Classifier: Programming Language :: Python :: 3.12
Requires-Dist: colorama (>=0.4.6,<0.5.0)
Requires-Dist: keyboard (>=0.13.5,<0.14.0)
Requires-Dist: python-time (>=0.3.0,<0.4.0)
Requires-Dist: random2 (>=1.0.2,<2.0.0)
